README.md
setup.cfg
setup.py
email_function_logger/__init__.py
email_function_logger/function_logger.py
email_function_logger/tests.py
email_function_logger.egg-info/PKG-INFO
email_function_logger.egg-info/SOURCES.txt
email_function_logger.egg-info/dependency_links.txt
email_function_logger.egg-info/requires.txt
email_function_logger.egg-info/top_level.txt