Metadata-Version: 2.1
Name: email-function-logger
Version: 1.1
Summary: A decorator to log information about a function and send it to your email
Home-page: https://github.com/arthurcerveira/Email-Function-Logger
Author: Arthur Cerveira
Author-email: aacerveira@inf.ufpel.edu.br
License: UNKNOWN
Download-URL: https://github.com/arthurcerveira/Email-Function-Logger/archive/v1.1.tar.gz
Keywords: log,email,function,logger
Platform: UNKNOWN
Classifier: Programming Language :: Python :: 3
Classifier: License :: OSI Approved :: MIT License
Classifier: Operating System :: OS Independent
Requires-Python: >=3.2
